stag/__init__.py
stag/_stag_internal.cpython-311-x86_64-linux-gnu.so
stag/cluster.py
stag/data.py
stag/graph.py
stag/graphio.py
stag/kde.py
stag/lsh.py
stag/neo4j.py
stag/random.py
stag/spectrum.py
stag/stag_internal.py
stag/stag_internal_wrap.cxx
stag/stag_internal_wrap.h
stag/utility.py
stag/eigen-3.4.0/.gitignore
stag/eigen-3.4.0/.gitlab-ci.yml
stag/eigen-3.4.0/.hgeol
stag/eigen-3.4.0/CMakeLists.txt
stag/eigen-3.4.0/COPYING.APACHE
stag/eigen-3.4.0/COPYING.BSD
stag/eigen-3.4.0/COPYING.GPL
stag/eigen-3.4.0/COPYING.LGPL
stag/eigen-3.4.0/COPYING.MINPACK
stag/eigen-3.4.0/COPYING.MPL2
stag/eigen-3.4.0/COPYING.README
stag/eigen-3.4.0/CTestConfig.cmake
stag/eigen-3.4.0/CTestCustom.cmake.in
stag/eigen-3.4.0/INSTALL
stag/eigen-3.4.0/README.md
stag/eigen-3.4.0/eigen3.pc.in
stag/eigen-3.4.0/signature_of_eigen3_matrix_library
stag/eigen-3.4.0/Eigen/Cholesky
stag/eigen-3.4.0/Eigen/CholmodSupport
stag/eigen-3.4.0/Eigen/Core
stag/eigen-3.4.0/Eigen/Dense
stag/eigen-3.4.0/Eigen/Eigen
stag/eigen-3.4.0/Eigen/Eigenvalues
stag/eigen-3.4.0/Eigen/Geometry
stag/eigen-3.4.0/Eigen/Householder
stag/eigen-3.4.0/Eigen/IterativeLinearSolvers
stag/eigen-3.4.0/Eigen/Jacobi
stag/eigen-3.4.0/Eigen/KLUSupport
stag/eigen-3.4.0/Eigen/LU
stag/eigen-3.4.0/Eigen/MetisSupport
stag/eigen-3.4.0/Eigen/OrderingMethods
stag/eigen-3.4.0/Eigen/PaStiXSupport
stag/eigen-3.4.0/Eigen/PardisoSupport
stag/eigen-3.4.0/Eigen/QR
stag/eigen-3.4.0/Eigen/QtAlignedMalloc
stag/eigen-3.4.0/Eigen/SPQRSupport
stag/eigen-3.4.0/Eigen/SVD
stag/eigen-3.4.0/Eigen/Sparse
stag/eigen-3.4.0/Eigen/SparseCholesky
stag/eigen-3.4.0/Eigen/SparseCore
stag/eigen-3.4.0/Eigen/SparseLU
stag/eigen-3.4.0/Eigen/SparseQR
stag/eigen-3.4.0/Eigen/StdDeque
stag/eigen-3.4.0/Eigen/StdList
stag/eigen-3.4.0/Eigen/StdVector
stag/eigen-3.4.0/Eigen/SuperLUSupport
stag/eigen-3.4.0/Eigen/UmfPackSupport
stag/eigen-3.4.0/Eigen/src/Cholesky/LDLT.h
stag/eigen-3.4.0/Eigen/src/Cholesky/LLT.h
stag-2.1.2.dist-info/METADATA
stag-2.1.2.dist-info/WHEEL
stag-2.1.2.dist-info/top_level.txt
stag-2.1.2.dist-info/RECORD
stag-2.1.2.dist-info/licenses/LICENSE
