Metadata-Version: 2.1
Name: stag
Version: 2.1.2
Summary: STAG: Spectral Toolkit of Algorithms for Graphs
Home-page: https://staglibrary.io
Author: Peter Macgregor
Author-email: <macgregor.pr@gmail.com>
Keywords: python,spectral,graph,algorithms,clustering,cheeger
Classifier: Development Status :: 5 - Production/Stable
Classifier: Intended Audience :: Education
Classifier: Programming Language :: Python :: 3
Classifier: Operating System :: MacOS :: MacOS X
Classifier: Operating System :: Microsoft :: Windows
Classifier: Operating System :: POSIX :: Linux
License-File: LICENSE
Requires-Dist: scipy
Requires-Dist: networkx
Requires-Dist: matplotlib
Requires-Dist: neo4j
Requires-Dist: numpy <2.0.0
